onyxgenai/__init__.py
onyxgenai/embed.py
onyxgenai/extract.py
onyxgenai/model.py
onyxgenai-1.0.5.dist-info/LICENSE
onyxgenai-1.0.5.dist-info/METADATA
onyxgenai-1.0.5.dist-info/WHEEL
onyxgenai-1.0.5.dist-info/top_level.txt
onyxgenai-1.0.5.dist-info/RECORD
