Metadata-Version: 2.1
Name: onyxgenai
Version: 1.0.5
Summary: Python SDK for interacting with Onyx Generative AI Services
License:                                  Apache License
Project-URL: Homepage, https://github.com/MetroStar/onyx-genai-sdk
Requires-Python: >=3.10
License-File: LICENSE
Requires-Dist: requests
Requires-Dist: spacy
Requires-Dist: PyPDF2
Requires-Dist: python-pptx
Provides-Extra: dev
Requires-Dist: pytest; extra == "dev"
Requires-Dist: ruff; extra == "dev"
